[
  {
    "uid": 1,
    "title": "Салат Греческий",
    "price": 289,
    "descr": "Микс салата, сухари, соус цезарь, курица, пармезан, черри",
    "gallery": "/../menuAroma/Salads/Greece.jpg",
    "category": "salads"
  },
  {
    "uid": 2,
    "title": "Салат с баклажанами и фетой",
    "price": 329,
    "descr": "Микс салата, баклажан в фритюре, помидор, фета, орех грецкий, чили сладкий, бальзамик, ароматное масло",
    "gallery": "/../menuAroma/Salads/салат с баклажанами и феттой.jpg",
    "category": "salads"
  },
  {
    "uid": 3,
    "title": "Салат Капрезе",
    "portion": 0,
    "price": 349,
    "descr": "Моцарела шарики, черри, руккола, песто, ароматное масло, бальзамик",
    "gallery": "/../menuAroma/Salads/Caprese.jpg",
    "category": "salads"
  },
  {
    "uid": 4,
    "title": "Цезарь с креветками",
    "portion": 0,
    "price": 379,
    "descr": "Микс салата, сухари, соус цезарь, креветки, черри , пармезан",
    "gallery": "/../menuAroma/Salads/Caesar with shrimp.jpg",
    "category": "salads"
  },
  {
    "uid": 5,
    "title": "Цезарь с курицей",
    "portion": 0,
    "price": 329,
    "descr": "Микс салата, сухари,соус цезарь, курица, пармезан,черри",
    "gallery": "/../menuAroma/Salads/Caesar with chicken.jpg",
    "category": "salads"
  },
  {
    "uid": 6,
    "title": "Салат с креветками и рукколой",
    "portion": 0,
    "price": 379,
    "descr": "Руккола,черри,авокадо,пармезан,креветки (обжаренные на чесночном масле), лимон, ароматное масло",
    "gallery": "/../menuAroma/Salads/Салат с креветками и рукколой.jpg",
    "category": "salads"
  },

  {
    "uid": 100,
    "title": "Паста Карбонара",
    "portion": 0,
    "price": 359,
    "descr": "Тальятелле, бекон, лук репчатый,чеснок, сливки, желток, пармезан",
    "gallery": "/../menuAroma/Pasta/Carbonara paste.jpg",
    "category": "pasta"
  },
  {
    "uid": 101,
    "title": "Паста с курицей и грибами",
    "portion": 0,
    "price": 369,
    "descr": "Тальятелле , курица,грибы,лук репчатый, чеснок, сливки,песто, пармезан",
    "gallery": "/../menuAroma/Pasta/Pasta with chicken and mushrooms.jpg",
    "category": "pasta"
  },
  {
    "uid": 102,
    "title": "Паста с креветками",
    "portion": 0,
    "price": 419,
    "descr": "Тальятелле, креветки ,лук красный, черри, руккола, сливки, чеснок, соевый, пармезан",
    "gallery": "/../menuAroma/Pasta/Pasta with shrimp.jpg",
    "category": "pasta"
  },
  {
    "uid": 103,
    "title": "WOK с курицей",
    "portion": 0,
    "price": 359,
    "descr": "Баветте, курица, грибы, перец болгарский, лук красный, фасоль стручковая, кунжутное масло,чеснок, черри, соевый, сладкий чили, терияки, кунжут",
    "gallery": "/../menuAroma/Pasta/Wok with chicken.jpg",
    "category": "pasta"
  },
  {
    "uid": 104,
    "title": "WOK с креветками",
    "portion": 0,
    "price": 419,
    "descr": "Баветте, креветки, лук красный, перец болгарский,фасоль стручковая,черри, грибы, чеснок, кунжутное масло, соевый, сладкий чили, терияки,кунжут",
    "gallery": "/../menuAroma/Pasta/ВОК с креветками.jpg",
    "category": "pasta"
  },
  {
    "uid": 105,
    "title": "Паста 4 сыра",
    "portion": 0,
    "price": 369,
    "descr": "Тальятелле, дор блю, сыр творожный, сыр сливочный, пармезан, сливки",
    "gallery": "/../menuAroma/Pasta/Паста 4 сыра.jpg",
    "category": "pasta"
  },

  {
    "uid": 400,
    "title": "Бефстроганов с картофельным пюре",
    "portion": 0,
    "price": 499,
    "descr": "Говядина, лук репчатый,чеснок, масло сливочное, сметана ,сливки + картофельное пюре + огурец соленый.",
    "gallery": "/../menuAroma/Hot dish/Beef Stroganoff with potato mash.jpg",
    "category": "hotDish"
  },
  {
    "uid": 401,
    "title": "Куриный стейк с картофельным пюре",
    "portion": 0,
    "price": 469,
    "descr": "Куриный стейк, фри или пюре, соус цезарь",
    "gallery": "/../menuAroma/Hot dish/Chicken Steak with Potato puree.jpg",
    "category": "hotDish"
  },
  {
    "uid": 402,
    "title": "Куриный стейк с картофелем фри",
    "portion": 0,
    "price": 469,
    "descr": "Куриный стейк, фри или пюре, соус цезарь",
    "gallery": "/../menuAroma/Hot dish/Chicken steak with French fries.jpg",
    "category": "hotDish"
  },
  {
    "uid": 403,
    "title": "Ризотто с морепродуктами",
    "portion": 0,
    "price": 519,
    "descr": "Рис, лук репчатый, чеснок, сливочное масло, кальмар, креветки, куркума, сыр творожный, сливки, пармезан",
    "gallery": "/../menuAroma/Hot dish/ризотто.jpg",
    "category": "hotDish"
  },
  {
    "uid": 500,
    "title": "Суп куриный",
    "portion": 0,
    "price": 239,
    "descr": "Наваристый ĸуриный бульон с лапшой, яйцом и ĸуриным филе, свежая зелень.",
    "gallery": "/../menuAroma/Soup/Soup with chicken.jpg",
    "category": "soup"
  },
  {
    "uid": 501,
    "title": "Крем-суп сырный",
    "portion": 0,
    "price": 259,
    "descr": "Лук репчатый,морковь, чеснок, картофель, сыр сливочный, сливки, пармезан.",
    "gallery": "/../menuAroma/Soup/крем суп сырный.jpg",
    "category": "soup"
  },
  {
    "uid": 502,
    "title": "Рамен с курицей",
    "portion": 0,
    "price": 299,
    "descr": "Бульон Рамен(соевый,чеснок,имбирь,бульон) , лапша яичная,курица,вакаме, яйцо, кунжут, лук зеленый.",
    "gallery": "/../menuAroma/Soup/Рамен.jpg",
    "category": "soup"
  },
  {
    "uid": 503,
    "title": "Сливочный суп с морепродуктами",
    "portion": 0,
    "price": 399,
    "descr": "Креветки, кальмары, черри, лук порей, сливки",
    "gallery": "/../menuAroma/Soup/Сливочный суп с морепродуктами.jpg",
    "category": "soup"
  },
  {
    "uid": 600,
    "title": "Брускетта с ростбифом",
    "portion": 0,
    "price": 339,
    "descr": "Креветки обжариваются в панцире с чесноĸом и соевом соусе и ĸусочĸом лимона, подается с дольĸой лимона и сладĸим чили",
    "gallery": "/../menuAroma/Snack/Брускетта с ростбифом.jpg",
    "category": "snacks"
  },
  {
    "uid": 601,
    "title": "Брускетта с лососем",
    "portion": 0,
    "price": 379,
    "descr": "",
    "weight": "",
    "gallery": "/../menuAroma/Snack/Брускетта с лососем.jpg",
    "category": "snacks"
  },
  {
    "uid": 614,
    "title": "Чиабата с курицей",
    "portion": 0,
    "price": 259,
    "descr": "Курица, гауда, корнишоны, помидоры, соус цезарь, лист салата",
    "weight": "",
    "gallery": "/../menuAroma/Snack/Чиабата с курицей.jpg",
    "category": "snacks"
  },
  {
    "uid": 602,
    "title": "Креветки темпура",
    "portion": 0,
    "price": 469,
    "descr": "Креветки обжариваются в панцире с чесноĸом и соевом соусе и ĸусочĸом лимона, подается с зеленью под соусом васаби",
    "gallery": "/../menuAroma/Snack/Shrimp tempura.jpg",
    "category": "snacks"
  },
  {
    "uid": 603,
    "title": "Сырная тарелка",
    "portion": 0,
    "price": 389,
    "descr": "Сыр моцарелла, майонез, яйца, панировочные сухари",
    "gallery": "/../menuAroma/Snack/Сырная тарелка.jpg",
    "category": "snacks"
  },
  {
    "uid": 604,
    "title": "Куриный паштет с вишнёвым конфитюром",
    "portion": 0,
    "price": 349,
    "descr": "",
    "gallery": "/../menuAroma/Snack/Chicken Pate with a cherry Confection.jpg",
    "category": "snacks"
  },

  {
    "uid": 605,
    "title": "Мидии запечённые под сыром",
    "portion": 0,
    "price": 429,
    "descr": "",
    "gallery": "/../menuAroma/Snack/Мидии.jpg",
    "category": "snacks"
  },
  {
    "uid": 606,
    "title": "Бри запечённый с грушей и мёдом",
    "portion": 0,
    "price": 449,
    "descr": "",
    "gallery": "/../menuAroma/Snack/Бри с грушей.jpg",
    "category": "snacks"
  },
  {
    "uid": 607,
    "title": "Бри запечённый с черри и розмарином",
    "portion": 0,
    "price": 419,
    "descr": "",
    "gallery": "/../menuAroma/Snack/Brie baked with cherry and rosemary.jpg",
    "category": "snacks"
  },
  {
    "uid": 608,
    "title": "Оливки/маслины",
    "portion": 0,
    "price": 209,
    "descr": "",
    "gallery": "/../menuAroma/Snack/Olive .jpg",
    "category": "snacks"
  },
  {
    "uid": 609,
    "title": "Картофель фри",
    "portion": 0,
    "price": 189,
    "descr": "",
    "editions": [
      {
        "uid": 60901,
        "title": "Картофель фри",
        "subtitle": "Маленькая порция - ",
        "price": 189,
        "gallery": "/../menuAroma/Snack/French fries.jpg",
        "weight": "150 гр."
      },
      {
        "uid": 60902,
        "title": "Картофель фри",
        "subtitle": "Большая порция - ",
        "difference": 50,
        "price": 239,
        "gallery": "/../menuAroma/Snack/French fries.jpg",
        "weight": "250 гр."
      }
    ],
    "gallery": "/../menuAroma/Snack/French fries.jpg",
    "category": "snacks"
  },
  {
    "uid": 610,
    "title": "Куриные наггетсы",
    "portion": 0,
    "price": 239,
    "descr": "",
    "editions": [
      {
        "uid": 61001,
        "subtitle": "Маленькая порция - ",
        "price": 239,
        "gallery": "/../menuAroma/Snack/Chicken nuggets.jpg",
        "weight": "150 гр."
      },
      {
        "uid": 61002,
        "subtitle": "Большая порция - ",
        "difference": "100",
        "price": 339,
        "gallery": "/../menuAroma/Snack/Chicken nuggets.jpg",
        "weight": "300 гр."
      }
    ],
    "gallery": "/../menuAroma/Snack/Chicken nuggets.jpg",
    "category": "snacks"
  },
  {
    "uid": 611,
    "title": "Гренки",
    "portion": 0,
    "price": 159,
    "descr": "",
    "gallery": "/../menuAroma/Snack/Croutons.jpg",
    "category": "snacks"
  },
  {
    "uid": 612,
    "title": "Фисташки",
    "portion": 0,
    "price": 279,
    "descr": "",
    "gallery": "/../menuAroma/Snack/Pistachios.jpg",
    "category": "snacks"
  },
  {
    "uid": 613,
    "title": "Солённый арахис",
    "portion": 0,
    "price": 149,
    "descr": "",
    "gallery": "/../menuAroma/Snack/Peanut.jpg",
    "category": "snacks"
  },
  {
    "uid": 650,
    "title": "Соус",
    "portion": 0,
    "price": 69,
    "descr": "",
    "gallery": "/../menuAroma/Snack/sauce.jpg",
    "category": "snacks",
    "editions": [
      {
        "uid": 65001,
        "subtitle": "Чесночный",
        "gallery": "/Snack/sauce.jpg",
        "price": 69
      },
      {
        "uid": 65002,
        "gallery": "/Snack/sauce.jpg",
        "subtitle": "Кисло-сладкий",
        "price": 69
      },
      {
        "uid": 65003,
        "gallery": "/Snack/sauce.jpg",
        "subtitle": "Сырный",
        "price": 69
      },
      {
        "uid": 65004,
        "gallery": "/Snack/sauce.jpg",
        "subtitle": "BBQ",
        "price": 69
      },
      {
        "uid": 65005,
        "gallery": "/Snack/sauce.jpg",
        "subtitle": "1000 островов",
        "price": 69
      }
    ]
  },
  {
    "uid": 651,
    "title": "Соус шрирача",
    "portion": 0,
    "price": 89,
    "descr": "",
    "gallery": "/../menuAroma/Snack/Sriracha.jpg",
    "category": "snacks"
  },
  {
    "uid": 690,
    "title": "Хлеб",
    "portion": 0,
    "price": 49,
    "descr": "",
    "gallery": "/../menuAroma/Snack/хлеб.jpg",
    "category": "snacks"
  },

  {
    "uid": 700,
    "title": "Кокосовый чизкейк",
    "portion": 0,
    "price": 319,
    "descr": "",
    "gallery": "/../menuAroma/Desserts/Coconut cheesecake.jpg",
    "category": "desserts"
  },
  {
    "uid": 701,
    "title": "Лимонный чизкейк",
    "portion": 0,
    "price": 319,
    "descr": "",
    "gallery": "/../menuAroma/Desserts/Lemon cheesecake.jpg",
    "category": "desserts"
  },
  {
    "uid": 703,
    "title": "Клубничная текилла",
    "portion": 0,
    "price": 289,
    "descr": "",
    "gallery": "/../menuAroma/Desserts/Strawberry tequila.jpg",
    "category": "desserts"
  },
  {
    "uid": 704,
    "title": "Хмельная вишня",
    "portion": 0,
    "price": 289,
    "descr": "Песочная ĸозинĸа с вишней",
    "gallery": "/../menuAroma/Desserts/Hop cherry.jpg",
    "category": "desserts"
  },
  {
    "uid": 800,
    "title": "Шарик мороженого",
    "portion": 0,
    "price": 89,
    "descr": "",
    "editions": [
      {
        "uid": 80001,
        "subtitle": "Сливочный - ",
        "price": 89,
        "gallery": "/Ice cream/Ice cream ball.jpg",
        "weight": "50 гр."
      },
      {
        "uid": 80002,
        "subtitle": "Шоколадный - ",
        "price": 89,
        "gallery": "/Ice cream/Ice cream ball.jpg",
        "weight": "50 гр."
      },
      {
        "uid": 80003,
        "subtitle": "Клубничный - ",
        "price": 89,
        "gallery": "/Ice cream/Ice cream ball.jpg",
        "weight": "50 гр."
      },
      {
        "uid": 80004,
        "subtitle": "Фисташковый - ",
        "price": 89,
        "gallery": "/Ice cream/Ice cream ball.jpg",
        "weight": "50 гр."
      }
    ],
    "gallery": "/Ice cream/Ice cream ball.jpg",
    "category": "iceCream"
  },
  {
    "uid": 801,
    "title": "Мороженое комбо",
    "portion": 0,
    "price": 249,
    "descr": "3 шарика мороженого + сироп/топинг + наполнитель",
    "gallery": "/Ice cream/Combo.jpg",
    "category": "iceCream"
  },
  {
    "uid": 890,
    "title": "Тертый орех",
    "portion": 0,
    "price": 49,
    "descr": "",
    "gallery": "/../menuAroma/Ice cream/.jpg",
    "category": "iceCream"
  },
  {
    "uid": 891,
    "title": "Шоколад",
    "portion": 0,
    "price": 49,
    "descr": "",
    "gallery": "/../menuAroma/Ice cream/.jpg",
    "category": "iceCream"
  },
  {
    "uid": 892,
    "title": "Маршмеллоу",
    "portion": 0,
    "price": 49,
    "descr": "",
    "gallery": "/../menuAroma/Ice cream/маршмеллоу.jpg",
    "category": "iceCream"
  },
  {
    "uid": 893,
    "title": "Банан",
    "portion": 0,
    "price": 49,
    "descr": "",
    "gallery": "/../menuAroma/Ice cream/.jpg",
    "category": "iceCream"
  },
  {
    "uid": 900,
    "title": "Классический",
    "portion": 0,
    "price": 219,
    "descr": "",
    "gallery": "/../menuAroma/Milkshake/Classic milkshake.jpg",
    "category": "milkshake"
  },
  {
    "uid": 901,
    "title": "Клубничный",
    "portion": 0,
    "price": 219,
    "descr": "",
    "gallery": "/../menuAroma/Milkshake/Strawberry milkshake.jpg",
    "category": "milkshake"
  },
  {
    "uid": 902,
    "title": "Банановый",
    "portion": 0,
    "price": 219,
    "descr": "",
    "gallery": "/../menuAroma/Milkshake/Banana milkshake.jpg",
    "category": "milkshake"
  },
  {
    "uid": 903,
    "title": "Шоколадный",
    "portion": 0,
    "price": 219,
    "descr": "",
    "gallery": "/../menuAroma/Milkshake/Chocolate milkshake.jpg",
    "category": "milkshake"
  },

  {
    "uid": 1000,
    "title": "Ягодный",
    "portion": 0,
    "price": 249,
    "descr": "",
    "gallery": "/../menuAroma/Smoothie/Berry smoothie.jpg",
    "category": "smoothie"
  },
  {
    "uid": 1001,
    "title": "Вишня-малина",
    "portion": 0,
    "price": 249,
    "descr": "",
    "gallery": "/../menuAroma/Smoothie/Cherry Raspberry Smoothie.jpg",
    "category": "smoothie"
  },
  {
    "uid": 1002,
    "title": "Груша-яблоко",
    "portion": 0,
    "price": 259,
    "descr": "",
    "gallery": "/../menuAroma/Smoothie/Smoothie Pear Apple.jpg",
    "category": "smoothie"
  },

  {
    "uid": 1100,
    "title": "Американо",
    "portion": 0,
    "price": 169,
    "descr": "",
    "weight": "180 мл.",
    "gallery": "/../menuAroma/Coffee/Americano.jpg",
    "category": "coffee"
  },
  {
    "uid": 1101,
    "title": "Двойной эспрессо",
    "portion": 0,
    "price": 139,
    "descr": "",
    "weight": "60 мл.",
    "gallery": "/../menuAroma/Coffee/двойной эспрессо.jpg",
    "category": "coffee"
  },
  {
    "uid": 1102,
    "title": "Капучино",
    "portion": 0,
    "price": 189,
    "descr": "",
    "weight": "250 мл.",
    "editions": [
      {
        "uid": 110201,
        "subtitle": "Маленький",
        "price": 189,
        "gallery": "/../menuAroma/Coffee/cappuccino.jpg",
        "weight": "250 мл."
      },
      {
        "uid": 110202,
        "subtitle": "Большой",
        "difference": "50 р.",
        "price": 219,
        "gallery": "/../menuAroma/Coffee/cappuccino.jpg",
        "weight": "400 мл."
      }
    ],
    "gallery": "/../menuAroma/Coffee/cappuccino.jpg",
    "category": "coffee"
  },
  {
    "uid": 1103,
    "title": "Латте",
    "portion": 0,
    "price": 219,
    "descr": "",
    "weight": "250 мл.",
    "gallery": "/../menuAroma/Coffee/Latte.jpg",
    "category": "coffee"
  },
  {
    "uid": 1104,
    "title": "Айс латте",
    "portion": 0,
    "price": 239,
    "descr": "",
    "weight": "350 мл.",
    "gallery": "/../menuAroma/Coffee/Ice latte.jpg",
    "category": "coffee"
  },
  {
    "uid": 1105,
    "title": "Бамбл",
    "portion": 0,
    "price": 219,
    "descr": "",
    "weight": "350 мл.",
    "gallery": "/../menuAroma/Coffee/Bumble.jpg",
    "category": "coffee"
  },
  {
    "uid": 1106,
    "title": "Раф",
    "portion": 0,
    "price": 279,
    "descr": "",
    "weight": "250 мл.",
    "gallery": "/../menuAroma/Coffee/Raf.jpg",
    "category": "coffee"
  },
  {
    "uid": 1107,
    "title": "Какао",
    "portion": 0,
    "price": 219,
    "descr": "",
    "weight": "250 мл.",
    "gallery": "/../menuAroma/Coffee/Cacao.jpg",
    "category": "coffee"
  },
  {
    "uid": 1200,
    "title": "Ягодный чай",
    "portion": 0,
    "price": 289,
    "descr": "",
    "editions": [
      {
        "uid": 120001,
        "subtitle": "Маленький - ",
        "price": 289,
        "gallery": "/../menuAroma/Tea/Ягодный.jpg",
        "weight": "0.5 л."
      },
      {
        "uid": 120002,
        "subtitle": "Большой - ",
        "difference": "50 р.",
        "price": 339,
        "gallery": "/../menuAroma/Tea/Ягодный.jpg",
        "weight": "1 л."
      }
    ],
    "gallery": "/../menuAroma/Tea/Ягодный.jpg",
    "category": "tea"
  },
  {
    "uid": 1201,
    "title": "Цитрусовый чай",
    "portion": 0,
    "price": 289,
    "descr": "",
    "editions": [
      {
        "uid": 120101,
        "subtitle": "Маленький - ",
        "price": 289,
        "gallery": "/../menuAroma/Tea/цитрусовый.jpg",
        "weight": "0.5 л."
      },
      {
        "uid": 120102,
        "subtitle": "Большой - ",
        "difference": "50 р.",
        "price": 339,
        "gallery": "/../menuAroma/Tea/цитрусовый.jpg",
        "weight": "1 л."
      }
    ],
    "gallery": "/../menuAroma/Tea/цитрусовый.jpg",
    "category": "tea"
  },

  {
    "uid": 1202,
    "title": "Облепиховый чай",
    "portion": 0,
    "price": 289,
    "descr": "",
    "editions": [
      {
        "uid": 120101,
        "subtitle": "Маленький - ",
        "price": 289,
        "weight": "0.5 л."
      },
      {
        "uid": 120102,
        "subtitle": "Большой - ",
        "difference": "50 р.",
        "price": 339,
        "weight": "1 л."
      }
    ],
    "gallery": "/../menuAroma/Tea/.jpg",
    "category": "tea"
  },
  {
    "uid": 1203,
    "title": "Чай малина-розмарин",
    "portion": 0,
    "price": 289,
    "descr": "",
    "editions": [
      {
        "uid": 120301,
        "subtitle": "Маленький - ",
        "price": 289,
        "gallery": "/../menuAroma/Tea/малина розмарин.jpg",
        "weight": "0.5 л."
      },
      {
        "uid": 120302,
        "subtitle": "Большой - ",
        "difference": "50 р.",
        "price": 339,
        "gallery": "/../menuAroma/Tea/малина розмарин.jpg",
        "weight": "1 л."
      }
    ],
    "gallery": "/../menuAroma/Tea/малина розмарин.jpg",
    "category": "tea"
  },
  {
    "uid": 1204,
    "title": "Чай клубника-базилик",
    "portion": 0,
    "price": 289,
    "descr": "",
    "editions": [
      {
        "uid": 120401,
        "subtitle": "Маленький - ",
        "price": 289,
        "gallery": "/../menuAroma/Tea/клубника базилик.jpg",
        "weight": "0.5 л."
      },
      {
        "uid": 120402,
        "subtitle": "Большой - ",
        "difference": "50 р.",
        "price": 339,
        "gallery": "/../menuAroma/Tea/клубника базилик.jpg",
        "weight": "1 л."
      }
    ],
    "gallery": "/../menuAroma/Tea/клубника базилик.jpg",
    "category": "tea"
  },
  {
    "uid": 1205,
    "title": "Чай вишня-корица",
    "portion": 0,
    "price": 289,
    "descr": "",
    "editions": [
      {
        "uid": 120501,
        "subtitle": "Маленький - ",
        "price": 289,
        "gallery": "/../menuAroma/Tea/вишня корица.jpg",
        "weight": "0.5 л."
      },
      {
        "uid": 120502,
        "subtitle": "Большой - ",
        "difference": "50 р.",
        "price": 339,
        "gallery": "/../menuAroma/Tea/вишня корица.jpg",
        "weight": "1 л."
      }
    ],
    "gallery": "/../menuAroma/Tea/вишня корица.jpg",
    "category": "tea"
  },

  {
    "uid": 1210,
    "title": "Чёрный чай",
    "portion": 0,
    "price": 219,
    "descr": "",
    "editions": [
      {
        "uid": 121001,
        "subtitle": "Маленький - ",
        "price": 219,
        "gallery": "/../menuAroma/Tea/black tea.jpg",
        "weight": "0.5 л."
      },
      {
        "uid": 121002,
        "subtitle": "Большой - ",
        "difference": "40 р.",
        "price": 259,
        "gallery": "/../menuAroma/Tea/black tea.jpg",
        "weight": "1 л."
      }
    ],
    "gallery": "/../menuAroma/Tea/black tea.jpg",
    "category": "tea"
  },
  {
    "uid": 1211,
    "title": "Чёрный чай c бергамотом",
    "portion": 0,
    "price": 219,
    "descr": "",
    "editions": [
      {
        "uid": 121101,
        "subtitle": "Маленький - ",
        "price": 219,
        "gallery": "/../menuAroma/Tea/black tea.jpg",
        "weight": "0.5 л."
      },
      {
        "uid": 121102,
        "subtitle": "Большой - ",
        "difference": "40 р.",
        "price": 259,
        "gallery": "/../menuAroma/Tea/black tea.jpg",
        "weight": "1 л."
      }
    ],
    "gallery": "/../menuAroma/Tea/black tea.jpg",
    "category": "tea"
  },
  {
    "uid": 1212,
    "title": "Зелёный чай",
    "portion": 0,
    "price": 219,
    "descr": "",
    "editions": [
      {
        "uid": 121201,
        "subtitle": "Маленький - ",
        "price": 219,
        "gallery": "/../menuAroma/Tea/зеленый чай.jpg",
        "weight": "0.5 л."
      },
      {
        "uid": 121202,
        "subtitle": "Большой - ",
        "difference": "40 р.",
        "price": 259,
        "gallery": "/../menuAroma/Tea/зеленый чай.jpg",
        "weight": "1 л."
      }
    ],
    "gallery": "/../menuAroma/Tea/зеленый чай.jpg",
    "category": "tea"
  },
  {
    "uid": 1213,
    "title": "Молочный улун",
    "portion": 0,
    "price": 219,
    "descr": "",
    "editions": [
      {
        "uid": 121301,
        "subtitle": "Маленький - ",
        "price": 219,
        "gallery": "/../menuAroma/Tea/Milk oolong.jpg",
        "weight": "0.5 л."
      },
      {
        "uid": 121302,
        "subtitle": "Большой - ",
        "difference": "50 р.",
        "price": 339,
        "gallery": "/../menuAroma/Tea/Milk oolong.jpg",
        "weight": "1 л."
      }
    ],
    "gallery": "/../menuAroma/Tea/Milk oolong.jpg",
    "category": "tea"
  },
  {
    "uid": 1214,
    "title": "Пуэр/Вишневый пуэр",
    "portion": 0,
    "price": 299,
    "descr": "",
    "editions": [
      {
        "uid": 121401,
        "subtitle": "Маленький - ",
        "price": 299,
        "gallery": "/../menuAroma/Tea/пуэр.jpg",
        "weight": "0.5 л."
      },
      {
        "uid": 121402,
        "subtitle": "Большой - ",
        "difference": "100 р.",
        "price": 399,
        "gallery": "/../menuAroma/Tea/пуэр.jpg",
        "weight": "1 л."
      }
    ],
    "gallery": "/../menuAroma/Tea/пуэр.jpg",
    "category": "tea"
  },

  {
    "uid": 1290,
    "title": "Чабрец",
    "portion": 0,
    "price": 19,
    "descr": "",
    "gallery": "/../menuAroma/Tea/чабрец.jpg",
    "category": "tea"
  },
  {
    "uid": 1291,
    "title": "Мята",
    "portion": 0,
    "price": 19,
    "descr": "",
    "gallery": "/../menuAroma/Tea/Мята.jpg",
    "category": "tea"
  },
  {
    "uid": 1292,
    "title": "Лимон",
    "portion": 0,
    "price": 19,
    "descr": "",
    "gallery": "/../menuAroma/Tea/лимон.jpg",
    "category": "tea"
  },
  {
    "uid": 1293,
    "title": "Мёд",
    "portion": 0,
    "price": 29,
    "descr": "",
    "gallery": "/../menuAroma/Tea/.jpg",
    "category": "tea"
  },
  {
    "uid": 1294,
    "title": "Имбирь",
    "portion": 0,
    "price": 29,
    "descr": "",
    "gallery": "/../menuAroma/Tea/.jpg",
    "category": "tea"
  },

  {
    "uid": 1300,
    "title": "Лимонад черника-лаванда",
    "portion": 0,
    "price": 249,
    "descr": "",
    "editions": [
      {
        "uid": 130001,
        "subtitle": "Стакан - ",
        "price": 249,
        "gallery": "/../menuAroma/Lemonade/черника-лаванда.jpg",
        "weight": "0.4 л"
      },
      {
        "uid": 130002,
        "subtitle": "Графин - ",
        "difference": "200 р.",
        "price": 449,
        "gallery": "/../menuAroma/Lemonade/черника-лаванда.jpg",
        "weight": "1 л."
      }
    ],
    "gallery": "/../menuAroma/Lemonade/черника-лаванда.jpg",
    "category": "lemonade"
  },
  {
    "uid": 1301,
    "title": "Лимонад пало-санто-банан",
    "portion": 0,
    "price": 249,
    "descr": "",
    "editions": [
      {
        "uid": 130101,
        "subtitle": "Стакан - ",
        "price": 249,
        "gallery": "/../menuAroma/Lemonade/Palo Santo Banana Lemonade.jpg",
        "weight": "0.4 л."
      },
      {
        "uid": 130102,
        "subtitle": "Графин - ",
        "difference": "200 р.",
        "price": 449,
        "gallery": "/../menuAroma/Lemonade/Palo Santo Banana Lemonade.jpg",
        "weight": "1 л."
      }
    ],
    "gallery": "/../menuAroma/Lemonade/Palo Santo Banana Lemonade.jpg",
    "category": "lemonade"
  },
  {
    "uid": 1302,
    "title": "Лимонад ладан-кокос",
    "portion": 0,
    "price": 249,
    "descr": "",
    "editions": [
      {
        "uid": 130201,
        "subtitle": "Стакан - ",
        "price": 249,
        "gallery": "/../menuAroma/Lemonade/Lemonade frankincense coconut.jpg",
        "weight": "0.4 л."
      },
      {
        "uid": 130202,
        "subtitle": "Графин - ",
        "difference": "200 р.",
        "price": 449,
        "gallery": "/../menuAroma/Lemonade/Lemonade frankincense coconut.jpg",
        "weight": "1 л."
      }
    ],
    "gallery": "/../menuAroma/Lemonade/Lemonade frankincense coconut.jpg",
    "category": "lemonade"
  },
  {
    "uid": 1303,
    "title": "Лимонад ежевика-гранат",
    "portion": 0,
    "price": 249,
    "descr": "",
    "editions": [
      {
        "uid": 130301,
        "subtitle": "Стакан - ",
        "price": 249,
        "gallery": "/../menuAroma/Lemonade/Лимонад ежевика гранат.jpg",
        "weight": "0.4 л."
      },
      {
        "uid": 130302,
        "subtitle": "Графин - ",
        "difference": "200 р.",
        "price": 449,
        "gallery": "/../menuAroma/Lemonade/Лимонад ежевика гранат.jpg",
        "weight": "1 л."
      }
    ],
    "gallery": "/../menuAroma/Lemonade/Лимонад ежевика гранат.jpg",
    "category": "lemonade"
  },
  {
    "uid": 1305,
    "title": "Лимонад классический",
    "portion": 0,
    "price": 249,
    "descr": "",
    "editions": [
      {
        "uid": 130501,
        "subtitle": "Стакан - ",
        "price": 249,
        "gallery": "/../menuAroma/Lemonade/Lemonade Classic.jpg",
        "weight": "0.4 л."
      },
      {
        "uid": 130502,
        "subtitle": "Графин - ",
        "difference": "200 р.",
        "price": 449,
        "gallery": "/../menuAroma/Lemonade/Lemonade Classic.jpg",
        "weight": "1 л."
      }
    ],
    "gallery": "/../menuAroma/Lemonade/Lemonade Classic.jpg",
    "category": "lemonade"
  },
  {
    "uid": 1306,
    "title": "Лимонад ягодный",
    "portion": 0,
    "price": 249,
    "editions": [
      {
        "uid": 130601,
        "subtitle": "Стакан - ",
        "price": 249,
        "gallery": "/../menuAroma/Lemonade/Berry lemonade.jpg",
        "weight": "0.4 л."
      },
      {
        "uid": 130602,
        "subtitle": "Графин - ",
        "difference": "200 р.",
        "price": 449,
        "gallery": "/../menuAroma/Lemonade/Berry lemonade.jpg",
        "weight": "1 л."
      }
    ],
    "gallery": "/../menuAroma/Lemonade/Berry lemonade.jpg",
    "category": "lemonade"
  },
  {
    "uid": 1307,
    "title": "Лимонад киви-фейхоа",
    "portion": 0,
    "price": 249,
    "editions": [
      {
        "uid": 130701,
        "subtitle": "Стакан - ",
        "price": 249,
        "gallery": "/../menuAroma/Lemonade/Kiwi feijoa lemonade.jpg",
        "weight": "0.4 л."
      },
      {
        "uid": 130702,
        "subtitle": "Графин - ",
        "difference": "200 р.",
        "price": 449,
        "gallery": "/../menuAroma/Lemonade/Kiwi feijoa lemonade.jpg",
        "weight": "1 л."
      }
    ],
    "gallery": "/../menuAroma/Lemonade/Kiwi feijoa lemonade.jpg",
    "category": "lemonade"
  },
  {
    "uid": 1308,
    "title": "Лимонад ананас-клюква",
    "portion": 0,
    "price": 249,
    "editions": [
      {
        "uid": 130801,
        "subtitle": "Стакан - ",
        "price": 249,
        "gallery": "/../menuAroma/Lemonade/Ананас клюква.jpg",
        "weight": "0.4 л."
      },
      {
        "uid": 130802,
        "subtitle": "Графин - ",
        "difference": "200 р.",
        "price": 449,
        "gallery": "/../menuAroma/Lemonade/Ананас клюква.jpg",
        "weight": "1 л."
      }
    ],
    "gallery": "/../menuAroma/Lemonade/Ананас клюква.jpg",
    "category": "lemonade"
  },
  {
    "uid": 1309,
    "title": "Мохито классический",
    "portion": 0,
    "price": 249,
    "editions": [
      {
        "uid": 130901,
        "subtitle": "Стакан - ",
        "price": 249,
        "gallery": "/../menuAroma/Lemonade/Mojito Lemonade.jpg",
        "weight": "0.4 л."
      },
      {
        "uid": 130902,
        "subtitle": "Графин - ",
        "difference": "200 р.",
        "price": 449,
        "gallery": "/../menuAroma/Lemonade/Mojito Lemonade.jpg",
        "weight": "1 л."
      }
    ],
    "gallery": "/../menuAroma/Lemonade/Mojito Lemonade.jpg",
    "category": "lemonade"
  },
  {
    "uid": 1310,
    "title": "Лимонад малина-розмарин",
    "portion": 0,
    "price": 249,
    "editions": [
      {
        "uid": 131001,
        "subtitle": "Стакан - ",
        "price": 249,
        "gallery": "/../menuAroma/Lemonade/Lemonade raspberry rosemary.jpg",
        "weight": "0.4 л."
      },
      {
        "uid": 131002,
        "subtitle": "Графин - ",
        "difference": "200 р.",
        "price": 449,
        "gallery": "/../menuAroma/Lemonade/Lemonade raspberry rosemary.jpg",
        "weight": "1 л."
      }
    ],
    "gallery": "/../menuAroma/Lemonade/Lemonade raspberry rosemary.jpg",
    "category": "lemonade"
  },
  {
    "uid": 1311,
    "title": "Лимонад вишня-мята",
    "portion": 0,
    "price": 249,
    "editions": [
      {
        "uid": 131101,
        "subtitle": "Стакан - ",
        "price": 249,
        "gallery": "/../menuAroma/Lemonade/Lemonade cherry mint.jpg",
        "weight": "0.4 л."
      },
      {
        "uid": 131102,
        "subtitle": "Графин - ",
        "difference": "200 р.",
        "price": 449,
        "gallery": "/../menuAroma/Lemonade/Lemonade cherry mint.jpg",
        "weight": "1 л."
      }
    ],
    "gallery": "/../menuAroma/Lemonade/Lemonade cherry mint.jpg",
    "category": "lemonade"
  },
  {
    "uid": 1400,
    "title": "Вода",
    "portion": 0,
    "price": 129,
    "descr": "",
    "weight": "0.5 л.",
    "editions": [
      {
        "uid": 140001,
        "subtitle": "Газированная вода - ",
        "price": 129,
        "gallery": "/../menuAroma/NonAlco/вода.jpg",
        "weight": "0.5 л."
      },
      {
        "uid": 140002,
        "subtitle": "Негазированная вода - ",
        "price": 129,
        "gallery": "/../menuAroma/NonAlco/вода.jpg",
        "weight": "0.5 л."
      }
    ],
    "gallery": "/../menuAroma/NonAlco/вода.jpg",
    "category": "drimk"
  },
  {
    "uid": 1401,
    "title": "Рычал-Су",
    "portion": 0,
    "price": 189,
    "descr": "",
    "gallery": "/../menuAroma/NonAlco/рычал.jpg",
    "category": "drimk",
    "weight": "0.5 л."
  },
  {
    "uid": 1402,
    "title": "Боржоми стекло",
    "portion": 0,
    "price": 289,
    "descr": "",
    "weight": "0.5 л.",
    "gallery": "/../menuAroma/NonAlco/боржоми.jpg",
    "category": "drimk"
  },
  {
    "uid": 1403,
    "title": "Натуральный сок",
    "portion": 0,
    "price": 289,
    "descr": "",
    "weight": "1 л.",
    "gallery": "/Drink/.jpg",
    "category": "drimk"
  },
  {
    "uid": 1404,
    "title": "Лимонад натахтари",
    "portion": 0,
    "price": 199,
    "descr": "",
    "weight": "0.5 л.",
    "gallery": "/../menuAroma/NonAlco/натахтари.jpg",
    "category": "drimk"
  },
  {
    "uid": 1405,
    "title": "Red Bull",
    "portion": 0,
    "price": 219,
    "descr": "",
    "weight": "0.25 л.",
    "gallery": "/../menuAroma/NonAlco/red bull.jpg",
    "category": "drimk"
  },
  {
    "uid": 1406,
    "title": "Adrenalin Rush",
    "portion": 0,
    "price": 189,
    "descr": "",
    "weight": "0.25 л.",
    "gallery": "/../menuAroma/NonAlco/adrenaline.jpg",
    "category": "drimk"
  },
  {
    "uid": 1407,
    "title": "Свежевыжатый сок",
    "portion": 0,
    "price": 229,
    "descr": "",
    "weight": "0.3 л.",
    "editions": [
      {
        "uid": 140701,
        "subtitle": "Апельсиновый - ",
        "gallery": "/../menuAroma/Fresh juice/Orange.jpg",
        "price": 229,
        "weight": "0.3 л."
      },
      {
        "uid": 140702,
        "subtitle": "Грейпфрутовый - ",
        "gallery": "/../menuAroma/Fresh juice/Грейпфрутовый.jpg",
        "price": 229,
        "weight": "0.3 л."
      },
      {
        "uid": 140703,
        "subtitle": "Лимонный - ",
        "gallery": "/../menuAroma/Fresh juice/Лимонный.jpg",
        "price": 229,
        "weight": "0.3 л."
      }
    ],
    "gallery": "/../menuAroma/Fresh juice/Orange.jpg",
    "category": "drimk"
  },

  {
    "uid": 1500,
    "title": "Пиво",
    "portion": 0,
    "price": 209,
    "descr": "",
    "weight": "0.5 л.",
    "editions": [
      {
        "uid": 150001,
        "subtitle": "Алкогольное - ",
        "gallery": "/../menuAroma/Alco/kozel.jpg",
        "price": 209,
        "weight": "0.5 л."
      },
      {
        "uid": 150002,
        "subtitle": "Безалкогольное - ",
        "gallery": "/../menuAroma/Alco/kozel.jpg",
        "price": 209,
        "weight": "0.5 л."
      }
    ],
    "gallery": "/../menuAroma/Alco/kozel.jpg",
    "category": "alcohol"
  },
  {
    "uid": 1501,
    "title": "Разливное пиво",
    "portion": 0,
    "price": 159,
    "descr": "Разливное пиво",
    "weight": "0.33 л.",
    "editions": [
      {
        "uid": 150101,
        "subtitle": "",
        "price": 159,
        "weight": "0.33 л."
      },
      {
        "uid": 150102,
        "subtitle": "",
        "difference": "40 р.",
        "price": 199,
        "weight": "0.5 л."
      }
    ],
    "gallery": "/Alcohol/.jpg",
    "category": "alcohol"
  },
  {
    "uid": 1503,
    "title": "Сидр White Phoenix",
    "portion": 0,
    "price": 249,
    "descr": "",
    "weight": "0.5 л.",
    "gallery": "/../menuAroma/Alco/white phoenix.jpg",
    "category": "alcohol"
  },
  {
    "uid": 1504,
    "title": "Импортное пиво",
    "portion": 0,
    "price": 389,
    "descr": "",
    "weight": "0.5 л.",
    "gallery": "/../menuAroma/Alco/schneider weisse.jpg",
    "category": "alcohol"
  }
]
